run.py
sonny/__init__.py
sonny/core.py
sonny-0.1.2.dist-info/METADATA
sonny-0.1.2.dist-info/RECORD
sonny-0.1.2.dist-info/WHEEL
sonny-0.1.2.dist-info/entry_points.txt
sonny-0.1.2.dist-info/top_level.txt
