Metadata-Version: 2.1
Name: sonny
Version: 0.1.2
Summary: A command line translation software.
Home-page: UNKNOWN
Author: suowei
Author-email: suowei_66@qq.com
License: MIT
